acunetix_sdk/__init__.py
acunetix_sdk/client_async.py
acunetix_sdk/client_base.py
acunetix_sdk/client_sync.py
acunetix_sdk/errors.py
acunetix_sdk/http_clients.py
acunetix_sdk/models/__init__.py
acunetix_sdk/models/agent.py
acunetix_sdk/models/common_settings.py
acunetix_sdk/models/excluded_hours.py
acunetix_sdk/models/export.py
acunetix_sdk/models/issue_tracker.py
acunetix_sdk/models/notification.py
acunetix_sdk/models/pagination.py
acunetix_sdk/models/report.py
acunetix_sdk/models/report_template.py
acunetix_sdk/models/scan.py
acunetix_sdk/models/scan_profile.py
acunetix_sdk/models/target.py
acunetix_sdk/models/target_group.py
acunetix_sdk/models/user.py
acunetix_sdk/models/utils.py
acunetix_sdk/models/vulnerability.py
acunetix_sdk/models/waf.py
acunetix_sdk/models/worker.py
acunetix_sdk/resources/__init__.py
acunetix_sdk/resources/agents_config.py
acunetix_sdk/resources/base_resource.py
acunetix_sdk/resources/excluded_hours.py
acunetix_sdk/resources/exports.py
acunetix_sdk/resources/issue_trackers.py
acunetix_sdk/resources/notifications.py
acunetix_sdk/resources/report_templates.py
acunetix_sdk/resources/reports.py
acunetix_sdk/resources/roles.py
acunetix_sdk/resources/scan_profiles.py
acunetix_sdk/resources/scans.py
acunetix_sdk/resources/target_groups.py
acunetix_sdk/resources/targets.py
acunetix_sdk/resources/user_groups.py
acunetix_sdk/resources/users.py
acunetix_sdk/resources/vulnerabilities.py
acunetix_sdk/resources/wafs.py
acunetix_sdk/resources/workers.py
acunetix_sdk-0.1.1.dist-info/LICENSE
acunetix_sdk-0.1.1.dist-info/METADATA
acunetix_sdk-0.1.1.dist-info/WHEEL
acunetix_sdk-0.1.1.dist-info/RECORD
