Metadata-Version: 2.3
Name: acunetix-sdk
Version: 0.1.1
Summary: A Python SDK for the Acunetix API, with sync and async support.
License: MIT
Author: John Doe
Author-email: johndoe@example.com
Requires-Python: >=3.11,<4.0
Classifier: License :: OSI Approved :: MIT License
Classifier: Programming Language :: Python :: 3
Classifier: Programming Language :: Python :: 3.11
Classifier: Programming Language :: Python :: 3.12
Classifier: Programming Language :: Python :: 3.13
Requires-Dist: httpx (>=0.27.0,<0.28.0)
Requires-Dist: pydantic (>=2.0.0,<3.0.0)
Requires-Dist: requests (>=2.31.0,<3.0.0)
